{"campaigns":[],"version":10,"site":"https://rapidpro.datos.gob.mx","flows":[{"base_language":"spa","action_sets":[{"y":0,"x":100,"destination":"86d9eb43-23bd-4b71-9a99-93905fd78b78","uuid":"372820c0-4c59-4655-b8ae-badacc0d9a4d","actions":[{"msg":{"spa":"Queremos hacerte dos preguntas rapidas sobre tu ultima consulta para poder mejorar el servicio de tu centro de salud."},"media":{},"type":"reply"},{"msg":{"spa":"Tu opinion sincera de los servicios de salud es muy importante para poder mejorarlos. Nadie sabra lo que contestes: es anonimo."},"media":{},"type":"reply"},{"msg":{"spa":"Primera pregunta, en la ultima cita de tu bebe te preguntaron o dieron consejos sobre la alimentacion de tu bebe? (Si/No)"},"media":{},"type":"reply"}]},{"y":496,"x":458,"destination":"86d9eb43-23bd-4b71-9a99-93905fd78b78","uuid":"53e86b59-d683-4b01-bee3-58827bbcc62d","actions":[{"msg":{"spa":"Disculpa, no te entendi. En la ultima cita de tu bebe te preguntaron o dieron consejos sobre la alimentacion de tu bebe? (Si/No)"},"media":{},"type":"reply"}]},{"y":705,"x":87,"destination":"4336b992-a251-42a1-abbb-60ae1278028e","uuid":"5ff03ef4-a20d-4f91-b57e-36df995b314b","actions":[{"msg":{"spa":"De acuerdo. Finalmente, pudiste preguntar todas tu dudas y preocupaciones sobre tu bebe, en caso de tenerlas, durante tu consulta? (Si/No)"},"media":{},"type":"reply"}]},{"y":1136,"x":135,"destination":null,"uuid":"7ed881be-220e-4d02-9165-cce4ef8dafe0","actions":[{"msg":{"spa":"Gracias por tu opinion! La utilizaremos, junto con la de otras mamas como tu, para revisar el desempeno del personal de salud y el servicio de tu clinica."},"media":{},"type":"reply"}]},{"y":909,"x":520,"destination":"4336b992-a251-42a1-abbb-60ae1278028e","uuid":"b2afdf66-4740-4873-8a9f-58149c3392e2","actions":[{"msg":{"spa":"Disculpa, no te entendi. Pudiste preguntar todas tu dudas y preocupaciones sobre tu bebe, en caso de tenerlas, durante tu consulta? (Si/No)"},"media":{},"type":"reply"}]}],"version":10,"flow_type":"F","entry":"372820c0-4c59-4655-b8ae-badacc0d9a4d","rule_sets":[{"uuid":"86d9eb43-23bd-4b71-9a99-93905fd78b78","rules":[{"test":{"test":{"spa":"si s sip"},"type":"contains_any"},"category":{"spa":"Si"},"destination":"5ff03ef4-a20d-4f91-b57e-36df995b314b","uuid":"cd6d26ff-0796-495f-8e1c-7fb05f746ce4","destination_type":"A"},{"test":{"test":{"spa":"no n nop"},"type":"contains_any"},"category":{"spa":"No"},"destination":"5ff03ef4-a20d-4f91-b57e-36df995b314b","uuid":"5b8fb6af-eb70-45be-919f-769060b7ede5","destination_type":"A"},{"test":{"test":"true","type":"true"},"category":{"spa":"Other"},"destination":"53e86b59-d683-4b01-bee3-58827bbcc62d","uuid":"a785727c-bdc3-4e68-bc49-cc57a094ad8b","destination_type":"A"}],"ruleset_type":"wait_message","label":"Response 1","operand":"@step.value","finished_key":null,"response_type":"","y":538,"x":83,"config":{}},{"uuid":"4336b992-a251-42a1-abbb-60ae1278028e","rules":[{"test":{"test":{"spa":"si s sip"},"type":"contains_any"},"category":{"spa":"Si"},"destination":"7ed881be-220e-4d02-9165-cce4ef8dafe0","uuid":"fd219225-c680-41ea-a168-05b54a865128","destination_type":"A"},{"test":{"test":{"spa":"no n nop"},"type":"contains_any"},"category":{"spa":"No"},"destination":"7ed881be-220e-4d02-9165-cce4ef8dafe0","uuid":"2dedea5f-bef7-4e6e-97a7-056c1feae2e8","destination_type":"A"},{"test":{"test":"true","type":"true"},"category":{"spa":"Other"},"destination":"b2afdf66-4740-4873-8a9f-58149c3392e2","uuid":"d24e028b-1325-445e-bb01-ac855a4507a2","destination_type":"A"}],"ruleset_type":"wait_message","label":"Response 2","operand":"@step.value","finished_key":null,"response_type":"","y":987,"x":101,"config":{}}],"metadata":{"expires":4320,"revision":3,"uuid":"3075ee5f-ecfa-48a0-a708-51cc64d3a7d8","name":"b_incentives_w49_d7","saved_on":"2017-05-03T15:38:21.293910Z"}}],"triggers":[]}
