{"campaigns":[],"version":10,"site":"https://rapidpro.datos.gob.mx","flows":[{"base_language":"spa","action_sets":[{"y":0,"x":100,"destination":null,"uuid":"1b3df6bc-bfc0-4b33-90be-1c46fa60cdbd","actions":[{"msg":{"spa":"Tener relaciones sexuales es seguro en el embarazo pero si sangras o sientes dolor ve a tu unidad de salud y dile al personal. Puede ser que debas abstenerte."},"media":{},"type":"reply"}]}],"version":10,"flow_type":"F","entry":"1b3df6bc-bfc0-4b33-90be-1c46fa60cdbd","rule_sets":[],"metadata":{"expires":4320,"revision":2,"uuid":"bf791600-a7e5-4ea2-bd9e-fa24fd4b47ec","name":"p_concerns_w19_d3","saved_on":"2017-05-02T22:59:08.832527Z"}}],"triggers":[]}
