{"campaigns":[],"version":10,"site":"https://rapidpro.datos.gob.mx","flows":[{"base_language":"spa","action_sets":[{"y":0,"x":100,"destination":null,"uuid":"9db2442e-2c2d-4644-95b4-42a1170b8532","actions":[{"msg":{"spa":"Si tienes gripa, tos o estas enferma, tu leche sigue siendo Buena para el bebe.Si necesitas medicina dile a tu doctor que estas amamantando para que lo considere"},"media":{},"type":"reply"}]}],"version":10,"flow_type":"F","entry":"9db2442e-2c2d-4644-95b4-42a1170b8532","rule_sets":[],"metadata":{"expires":10080,"revision":3,"uuid":"e7aabb79-9a66-4933-b37d-406928916043","name":"b_concerns_w8_d4","saved_on":"2017-05-08T18:32:26.189852Z"}}],"triggers":[]}
