{"campaigns":[{"events":[{"event_type":"F","relative_to":{"key":"rp_mialerta_time","label":"rp-miAlerta-time"},"delivery_hour":-1,"message":null,"offset":1,"flow":{"name":"miAlerta_followUp","uuid":"26e6da43-f554-4c97-965b-563b3c16a6ed"},"unit":"H","uuid":"5c24f76a-0ce6-4a74-8793-6fa6b176b26a"},{"event_type":"F","relative_to":{"key":"rp_mialerta_time","label":"rp-miAlerta-time"},"delivery_hour":-1,"message":null,"offset":1,"flow":{"name":"miAlerta_followUp","uuid":"26e6da43-f554-4c97-965b-563b3c16a6ed"},"unit":"D","uuid":"1dacf9df-4d5f-42eb-aa64-9a1dc22b6a4d"}],"group":{"name":"MIALERTA","uuid":"95dac879-a692-4d86-a6e9-79b9bf0fb856"},"uuid":"1bbeb1b1-160f-421c-8c82-a6b015eec89a","name":"MiAlerta"}],"version":10,"site":"https://rapidpro.datos.gob.mx","flows":[{"base_language":"spa","action_sets":[{"y":449,"x":484,"destination":"fbd520eb-88f0-44b2-812e-e82a32b9dede","uuid":"e18be9df-0a32-455c-b15e-ae630507ff25","actions":[{"msg":{"spa":"Perfecto @contact.rp_name. Se comunicaron contigo o pudiste comunicarte al 01-800-628-3762? (Si/No)"},"media":{},"type":"reply"}]},{"y":518,"x":799,"destination":"fbd520eb-88f0-44b2-812e-e82a32b9dede","uuid":"d7cabf44-33ad-4464-9595-e86704bf22b7","actions":[{"msg":{"spa":"No entendi tu respuesta. Pudiste se comunicaron contigo o llamaste al 01-800-628-3762? (Si/No)"},"media":{},"type":"reply"}]},{"y":311,"x":1013,"destination":null,"uuid":"2816abf9-dedc-4dc1-aad0-32ab91005a2f","actions":[{"msg":{"spa":"Por favor comunIcate al 01-800-628-3762 para solucionar tu emergencia. Ahi recibiras ayuda inmediata."},"media":{},"type":"reply"}]},{"y":773,"x":363,"destination":"1723a545-49e7-4ede-a65a-1081e862b680","uuid":"4d480f3f-b7b8-4ecb-80f1-b6cb6429556a","actions":[{"msg":{"spa":"Estas en buenas manos, no te preocupes. Ellos se encargar\u00e1n de darle seguimiento a tu caso. Si tienes otra preocupacion, escribenos."},"media":{},"type":"reply"}]},{"y":1071,"x":512,"destination":null,"uuid":"1723a545-49e7-4ede-a65a-1081e862b680","actions":[{"type":"del_group","groups":[{"name":"MIALERTA","uuid":"95dac879-a692-4d86-a6e9-79b9bf0fb856"}]}]},{"y":137,"x":573,"destination":"599cfe22-7ed9-4a47-8451-326cf763df70","uuid":"0926eb01-6d63-43f7-b941-d3e8a6220cf9","actions":[{"msg":{"spa":"Hola @contact.rp_name, has recibido asistencia para tu problema de salud? (Si/No)"},"media":{},"type":"reply"}]},{"y":173,"x":868,"destination":"599cfe22-7ed9-4a47-8451-326cf763df70","uuid":"4119f34c-430d-44bc-bec4-70e3a7a7b51e","actions":[{"msg":{"spa":"Disculpame, no entendi. Has recibido asistencia para tu problema de salud? (Si/No)"},"media":{},"type":"reply"}]},{"y":776,"x":666,"destination":"1723a545-49e7-4ede-a65a-1081e862b680","uuid":"dfef509c-88fe-44cf-9dbe-9200fdc6bc86","actions":[{"msg":{"spa":"Si necesitas mas asistencia, por favor comunIcate inmediatamente al 01-800-628-3762 para solucionar tu emergencia. Ahi recibiras ayuda inmediata."},"media":{},"type":"reply"}]}],"version":10,"flow_type":"F","entry":"0926eb01-6d63-43f7-b941-d3e8a6220cf9","rule_sets":[{"uuid":"fbd520eb-88f0-44b2-812e-e82a32b9dede","rules":[{"test":{"test":{"spa":"s"},"type":"starts"},"category":{"spa":"Si"},"destination":"4d480f3f-b7b8-4ecb-80f1-b6cb6429556a","uuid":"e03a3015-573e-4939-bde0-e153710587ee","destination_type":"A"},{"test":{"test":{"spa":"n"},"type":"starts"},"category":{"spa":"No"},"destination":"dfef509c-88fe-44cf-9dbe-9200fdc6bc86","uuid":"93e3f62c-a615-489a-905e-8243a2d6edc0","destination_type":"A"},{"test":{"test":"true","type":"true"},"category":{"spa":"Other"},"destination":"d7cabf44-33ad-4464-9595-e86704bf22b7","uuid":"0bb09008-e2aa-45b6-abcc-9d178e868f47","destination_type":"A"}],"ruleset_type":"wait_message","label":"Response 2_s","operand":"@step.value","finished_key":null,"response_type":"","y":634,"x":449,"config":{}},{"uuid":"599cfe22-7ed9-4a47-8451-326cf763df70","rules":[{"test":{"test":{"spa":"s"},"type":"starts"},"category":{"spa":"Si"},"destination":"e18be9df-0a32-455c-b15e-ae630507ff25","uuid":"ec1d2061-5c12-4a9e-bb1e-e86264d77851","destination_type":"A"},{"test":{"test":{"spa":"n"},"type":"starts"},"category":{"spa":"No"},"destination":"2816abf9-dedc-4dc1-aad0-32ab91005a2f","uuid":"483a7962-3507-469d-9e37-f3a3117b3c9e","destination_type":"A"},{"test":{"test":"true","type":"true"},"category":{"spa":"Other"},"destination":"4119f34c-430d-44bc-bec4-70e3a7a7b51e","uuid":"a7baff6f-58d6-4559-9443-5cf08a29ad16","destination_type":"A"}],"ruleset_type":"wait_message","label":"Response 1_s","operand":"@step.value","finished_key":null,"response_type":"","y":275,"x":538,"config":{}}],"metadata":{"expires":10080,"saved_on":"2017-05-02T23:37:42.941571Z","uuid":"26e6da43-f554-4c97-965b-563b3c16a6ed","name":"miAlerta_followUp","revision":2}}],"triggers":[]}
