{"campaigns":[],"version":10,"site":"https://rapidpro.datos.gob.mx","flows":[{"base_language":"spa","action_sets":[{"y":0,"x":537,"destination":null,"uuid":"a6f4dee5-a4cf-49a8-a6ba-663c7ef95e6e","actions":[{"msg":{"spa":"Manten a tu bebe lejos de familiares que tengan infecciones. Cualquier resfriado o gripa puede afectar mucho a tu bebe prematuro"},"media":{},"type":"reply"}]}],"version":10,"flow_type":"F","entry":"a6f4dee5-a4cf-49a8-a6ba-663c7ef95e6e","rule_sets":[],"metadata":{"expires":1440,"revision":3,"uuid":"318fc751-bbed-4ec3-81d8-30285a9e498f","name":"prematuro3_2","saved_on":"2017-05-03T15:35:33.061429Z"}}],"triggers":[]}
